{
  "templates": {
    "type": "JSON",
    "content": [
      {
        "id": "150364573",
        "Flight": "WS2105",
        "PickupDate": "2026-01-17",
        "PickupTime": "03:20",
        "HotelName": "Caribe Deluxe Princess",
        "HotelNumber": 13616
      },
      {
        "id": "147099843",
        "Flight": "WS2707",
        "PickupDate": "2026-01-17",
        "PickupTime": "10:00",
        "HotelName": "Caribe Deluxe Princess",
        "HotelNumber": 13616
      },
      {
        "id": "147099303",
        "Flight": "WS2707",
        "PickupDate": "2026-01-17",
        "PickupTime": "10:00",
        "HotelName": "Caribe Deluxe Princess",
        "HotelNumber": 13616
      },
      {
        "id": "149424203",
        "Flight": "WS2653",
        "PickupDate": "2026-01-17",
        "PickupTime": "08:45",
        "HotelName": "Caribe Deluxe Princess",
        "HotelNumber": 13616
      },
      {
        "id": "148923653",
        "Flight": "WS2705",
        "PickupDate": "2026-01-17",
        "PickupTime": "10:30",
        "HotelName": "Caribe Deluxe Princess",
        "HotelNumber": 13616
      },
      {
        "id": "461-2671785",
        "Flight": "TOM057",
        "PickupDate": "2026-01-17",
        "PickupTime": "⚠️",
        "HotelName": "Caribe Deluxe Princess",
        "HotelNumber": 13616
      },
      {
        "id": "461-2671785",
        "Flight": "TOM057",
        "PickupDate": "2026-01-17",
        "PickupTime": "13:55",
        "HotelName": "Caribe Deluxe Princess",
        "HotelNumber": 13616
      }
    ],
    "source": {
      "data_source": "Google Sheets (Private)",
      "update_frequency": "Automated"
    }
  }
}