{
  "templates": {
    "type": "JSON",
    "content": [
      {
        "id": "147139433",
        "Flight": "WS2913",
        "PickupDate": "2025-11-11",
        "PickupTime": "10:30",
        "HotelName": "Caribe Deluxe Princess",
        "HotelNumber": 13616
      },
      {
        "id": "147141133",
        "Flight": "WS2913",
        "PickupDate": "2025-11-11",
        "PickupTime": "10:30",
        "HotelName": "Caribe Deluxe Princess",
        "HotelNumber": 13616
      },
      {
        "id": "147139943",
        "Flight": "WS2913",
        "PickupDate": "2025-11-11",
        "PickupTime": "10:30",
        "HotelName": "Caribe Deluxe Princess",
        "HotelNumber": 13616
      },
      {
        "id": "145683373",
        "Flight": "WS2103",
        "PickupDate": "2025-11-11",
        "PickupTime": "12:15",
        "HotelName": "Caribe Deluxe Princess",
        "HotelNumber": 13616
      },
      {
        "id": "461-2680528",
        "Flight": "TS187",
        "PickupDate": "2025-11-11",
        "PickupTime": "12:40",
        "HotelName": "Caribe Deluxe Princess",
        "HotelNumber": 13616
      },
      {
        "id": "147138363",
        "Flight": "WS2913",
        "PickupDate": "2025-11-11",
        "PickupTime": "10:30",
        "HotelName": "Caribe Deluxe Princess",
        "HotelNumber": 13616
      },
      {
        "id": "461-2694710",
        "Flight": "TOM119",
        "PickupDate": "2025-11-11",
        "PickupTime": "14:25",
        "HotelName": "Caribe Deluxe Princess",
        "HotelNumber": 13616
      }
    ],
    "source": {
      "data_source": "Google Sheets (Private)",
      "update_frequency": "Automated"
    }
  }
}